Metadata-Version: 2.1
Name: agentlayer
Version: 0.1
Summary: Agent Layer
Author: Delip Rao
Author-email: deliprao@gmail.com
License-File: LICENSE
